AR_TESTS/FIFO_TEST_AR4/logs/annotated/ibex_fetch_fifo.v
//      // verilator_coverage annotation
        // Copyright lowRISC contributors.
        // Copyright 2018 ETH Zurich and University of Bologna, see also CREDITS.md.
        // Licensed under the Apache License, Version 2.0, see LICENSE for details.
        // SPDX-License-Identifier: Apache-2.0
        
        /**
         * Fetch Fifo for 32 bit memory interface
         *
         * input port: send address and data to the FIFO
         * clear_i clears the FIFO for the following cycle, including any new request
         */
        
         `include "rtl/prim_assert.sv"
        
         module ibex_fetch_fifo #(
           parameter int unsigned NUM_REQS = 2,
           parameter bit          ResetAll = 1'b0
         ) (
 002000    input  logic                clk_i,
%000004    input  logic                rst_ni,
         
           // control signals
 000020    input  logic                clear_i,   // clears the contents of the FIFO
%000000    output logic [NUM_REQS-1:0] busy_o,
         
           // input port
 000066    input  logic                in_valid_i,
 000047    input  logic [31:0]         in_addr_i,
 000043    input  logic [31:0]         in_rdata_i,
 000065    input  logic                in_err_i,
         
           // output port
 000068    output logic                out_valid_o,
 000020    input  logic                out_ready_i,
%000000    output logic [31:0]         out_addr_o,
 000032    output logic [31:0]         out_rdata_o,
 000065    output logic                out_err_o,
%000000    output logic                out_err_plus2_o
         );
         
           localparam int unsigned DEPTH = NUM_REQS+1;
         
           // index 0 is used for output
%000000    logic [DEPTH-1:0] [31:0]  rdata_d,   rdata_q;
%000000    logic [DEPTH-1:0]         err_d,     err_q;
%000000    logic [DEPTH-1:0]         valid_d,   valid_q;
%000000    logic [DEPTH-1:0]         lowest_free_entry;
%000000    logic [DEPTH-1:0]         valid_pushed, valid_popped;
%000000    logic [DEPTH-1:0]         entry_en;
         
 000060    logic                     pop_fifo;
 000042    logic             [31:0]  rdata, rdata_unaligned;
%000000    logic                     err,   err_unaligned, err_plus2;
%000000    logic                     valid, valid_unaligned;
         
 000060    logic                     aligned_is_compressed, unaligned_is_compressed;
         
 000070    logic                     addr_incr_two;
%000000    logic [31:1]              instr_addr_next;
%000000    logic [31:1]              instr_addr_d, instr_addr_q;
 000038    logic                     instr_addr_en;
 000049    logic                     unused_addr_in;
         
           /////////////////
           // Output port //
           /////////////////
         
           assign rdata = valid_q[0] ? rdata_q[0] : in_rdata_i;
           assign err   = valid_q[0] ? err_q[0]   : in_err_i;
           assign valid = valid_q[0] | in_valid_i;
         
           // The FIFO contains word aligned memory fetches, but the instructions contained in each entry
           // might be half-word aligned (due to compressed instructions)
           // e.g.
           //              | 31               16 | 15               0 |
           // FIFO entry 0 | Instr 1 [15:0]      | Instr 0 [15:0]     |
           // FIFO entry 1 | Instr 2 [15:0]      | Instr 1 [31:16]    |
           //
           // The FIFO also has a direct bypass path, so a complete instruction might be made up of data
           // from the FIFO and new incoming data.
           //
         
           // Construct the output data for an unaligned instruction
           assign rdata_unaligned = valid_q[1] ? {rdata_q[1][15:0], rdata[31:16]} :
                                                 {in_rdata_i[15:0], rdata[31:16]};
         
           // If entry[1] is valid, an error can come from entry[0] or entry[1], unless the
           // instruction in entry[0] is compressed (entry[1] is a new instruction)
           // If entry[1] is not valid, and entry[0] is, an error can come from entry[0] or the incoming
           // data, unless the instruction in entry[0] is compressed
           // If entry[0] is not valid, the error must come from the incoming data
           assign err_unaligned   = valid_q[1] ? ((err_q[1] & ~unaligned_is_compressed) | err_q[0]) :
                                                 ((valid_q[0] & err_q[0]) |
                                                  (in_err_i & (~valid_q[0] | ~unaligned_is_compressed)));
         
           // Record when an error is caused by the second half of an unaligned 32bit instruction.
           // Only needs to be correct when unaligned and if err_unaligned is set
           assign err_plus2       = valid_q[1] ? (err_q[1] & ~err_q[0]) :
                                                 (in_err_i & valid_q[0] & ~err_q[0]);
         
           // An uncompressed unaligned instruction is only valid if both parts are available
           assign valid_unaligned = valid_q[1] ? 1'b1 :
                                                 (valid_q[0] & in_valid_i);
         
           // If there is an error, rdata is unknown
           assign unaligned_is_compressed = (rdata[17:16] != 2'b11) & ~err;
           assign aligned_is_compressed   = (rdata[ 1: 0] != 2'b11) & ~err;
         
           ////////////////////////////////////////
           // Instruction aligner (if unaligned) //
           ////////////////////////////////////////
         
%000001    always_comb begin
 000200      if (out_addr_o[1]) begin
               // unaligned case
 000200        out_rdata_o     = rdata_unaligned;
 000200        out_err_o       = err_unaligned;
 000200        out_err_plus2_o = err_plus2;
         
 000274        if (unaligned_is_compressed) begin
 000274          out_valid_o = valid;
 000326        end else begin
 000326          out_valid_o = valid_unaligned;
               end
 000800      end else begin
               // aligned case
 000800        out_rdata_o     = rdata;
 000800        out_err_o       = err;
 000800        out_err_plus2_o = 1'b0;
 000800        out_valid_o     = valid;
             end
           end
         
           /////////////////////////
           // Instruction address //
           /////////////////////////
         
           // Update the address on branches and every time an instruction is driven
           assign instr_addr_en = clear_i | (out_ready_i & out_valid_o);
         
           // Increment the address by two every time a compressed instruction is popped
           assign addr_incr_two = instr_addr_q[1] ? unaligned_is_compressed :
                                                    aligned_is_compressed;
         
           assign instr_addr_next = (instr_addr_q[31:1] +
                                     // Increment address by 4 or 2
                                     {29'd0,~addr_incr_two,addr_incr_two});
         
           assign instr_addr_d = clear_i ? in_addr_i[31:1] :
                                           instr_addr_next;
         
           if (ResetAll) begin : g_instr_addr_ra
             always_ff @(posedge clk_i or negedge rst_ni) begin
               if (!rst_ni) begin
                 instr_addr_q <= '0;
               end else if (instr_addr_en) begin
                 instr_addr_q <= instr_addr_d;
               end
             end
           end else begin : g_instr_addr_nr
 000999      always_ff @(posedge clk_i) begin
 000164        if (instr_addr_en) begin
 000164          instr_addr_q <= instr_addr_d;
               end
             end
           end
         
           // Output PC of current instruction
           assign out_addr_o      = {instr_addr_q, 1'b0};
         
           // The LSB of the address is unused, since all addresses are halfword aligned
           assign unused_addr_in = in_addr_i[0];
         
           /////////////////
           // FIFO status //
           /////////////////
         
           // Indicate the fill level of fifo-entries. This is used to determine when a new request can be
           // made on the bus. The prefetch buffer only needs to know about the upper entries which overlap
           // with NUM_REQS.
           assign busy_o = valid_q[DEPTH-1:DEPTH-NUM_REQS];
         
           /////////////////////
           // FIFO management //
           /////////////////////
         
           // Since an entry can contain unaligned instructions, popping an entry can leave the entry valid
           assign pop_fifo = out_ready_i & out_valid_o & (~aligned_is_compressed | out_addr_o[1]);
         
           for (genvar i = 0; i < (DEPTH - 1); i++) begin : g_fifo_next
             // Calculate lowest free entry (write pointer)
             if (i == 0) begin : g_ent0
               assign lowest_free_entry[i] = ~valid_q[i];
             end else begin : g_ent_others
               assign lowest_free_entry[i] = ~valid_q[i] & valid_q[i-1];
             end
         
             // An entry is set when an incoming request chooses the lowest available entry
             assign valid_pushed[i] = (in_valid_i & lowest_free_entry[i]) |
                                      valid_q[i];
             // Popping the FIFO shifts all entries down
             assign valid_popped[i] = pop_fifo ? valid_pushed[i+1] : valid_pushed[i];
             // All entries are wiped out on a clear
             assign valid_d[i] = valid_popped[i] & ~clear_i;
         
             // data flops are enabled if there is new data to shift into it, or
             assign entry_en[i] = (valid_pushed[i+1] & pop_fifo) |
                                  // a new request is incoming and this is the lowest free entry
                                  (in_valid_i & lowest_free_entry[i] & ~pop_fifo);
         
             // take the next entry or the incoming data
             assign rdata_d[i]  = valid_q[i+1] ? rdata_q[i+1] : in_rdata_i;
             assign err_d  [i]  = valid_q[i+1] ? err_q  [i+1] : in_err_i;
           end
           // The top entry is similar but with simpler muxing
           assign lowest_free_entry[DEPTH-1] = ~valid_q[DEPTH-1] & valid_q[DEPTH-2];
           assign valid_pushed     [DEPTH-1] = valid_q[DEPTH-1] | (in_valid_i & lowest_free_entry[DEPTH-1]);
           assign valid_popped     [DEPTH-1] = pop_fifo ? 1'b0 : valid_pushed[DEPTH-1];
           assign valid_d [DEPTH-1]          = valid_popped[DEPTH-1] & ~clear_i;
           assign entry_en[DEPTH-1]          = in_valid_i & lowest_free_entry[DEPTH-1];
           assign rdata_d [DEPTH-1]          = in_rdata_i;
           assign err_d   [DEPTH-1]          = in_err_i;
         
           ////////////////////
           // FIFO registers //
           ////////////////////
         
 000999    always_ff @(posedge clk_i or negedge rst_ni) begin
 000019      if (!rst_ni) begin
 000980        valid_q <= '0;
 000019      end else begin
 000019        valid_q <= valid_d;
             end
           end
         
 000520    for (genvar i = 0; i < DEPTH; i++) begin : g_fifo_regs
             if (ResetAll) begin : g_rdata_ra
               always_ff @(posedge clk_i or negedge rst_ni) begin
                 if (!rst_ni) begin
                   rdata_q[i] <= '0;
                   err_q[i]   <= '0;
                 end else if (entry_en[i]) begin
                   rdata_q[i] <= rdata_d[i];
                   err_q[i]   <= err_d[i];
                 end
               end
             end else begin : g_rdata_nr
 002997        always_ff @(posedge clk_i) begin
 000520          if (entry_en[i]) begin
 000520            rdata_q[i] <= rdata_d[i];
 000520            err_q[i]   <= err_d[i];
                 end
               end
             end
           end
         
           ////////////////
           // Assertions //
           ////////////////
         
           // Must not push and pop simultaneously when FIFO full.
           `ASSERT(IbexFetchFifoPushPopFull,
               (in_valid_i && pop_fifo) |-> (!valid_q[DEPTH-1] || clear_i))
         
           // Must not push to FIFO when full.
           `ASSERT(IbexFetchFifoPushFull,
               (in_valid_i) |-> (!valid_q[DEPTH-1] || clear_i))
         
         endmodule

AR_TESTS/FIFO_TEST_AR4/logs/ibex_fetch_fifo.vcd
$version Generated by VerilatedVcd $end
$timescale 1ns $end

 $scope module TOP $end
  $var wire  2 > busy_o [1:0] $end
  $var wire  1 = clear_i $end
  $var wire  1 ; clk_i $end
  $var wire 32 @ in_addr_i [31:0] $end
  $var wire  1 B in_err_i $end
  $var wire 32 A in_rdata_i [31:0] $end
  $var wire  1 ? in_valid_i $end
  $var wire 32 E out_addr_o [31:0] $end
  $var wire  1 G out_err_o $end
  $var wire  1 H out_err_plus2_o $end
  $var wire 32 F out_rdata_o [31:0] $end
  $var wire  1 D out_ready_i $end
  $var wire  1 C out_valid_o $end
  $var wire  1 < rst_ni $end
  $scope module ibex_fetch_fifo $end
   $var wire 32 Q DEPTH [31:0] $end
   $var wire 32 O NUM_REQS [31:0] $end
   $var wire  1 P ResetAll $end
   $var wire  1 2 addr_incr_two $end
   $var wire  1 0 aligned_is_compressed $end
   $var wire  2 > busy_o [1:0] $end
   $var wire  1 = clear_i $end
   $var wire  1 ; clk_i $end
   $var wire  3 ) entry_en [2:0] $end
   $var wire  1 - err $end
   $var wire  3 & err_d [2:0] $end
   $var wire  1 / err_plus2 $end
   $var wire  3 9 err_q [2:0] $end
   $var wire  1 . err_unaligned $end
   $var wire 32 @ in_addr_i [31:0] $end
   $var wire  1 B in_err_i $end
   $var wire 32 A in_rdata_i [31:0] $end
   $var wire  1 ? in_valid_i $end
   $var wire 31 4 instr_addr_d [31:1] $end
   $var wire  1 5 instr_addr_en $end
   $var wire 31 3 instr_addr_next [31:1] $end
   $var wire 31 : instr_addr_q [31:1] $end
   $var wire  3 J lowest_free_entry [2:0] $end
   $var wire 32 E out_addr_o [31:0] $end
   $var wire  1 G out_err_o $end
   $var wire  1 H out_err_plus2_o $end
   $var wire 32 F out_rdata_o [31:0] $end
   $var wire  1 D out_ready_i $end
   $var wire  1 C out_valid_o $end
   $var wire  1 * pop_fifo $end
   $var wire 32 + rdata [31:0] $end
   $var wire 96 # rdata_d [95:0] $end
   $var wire 96 6 rdata_q [95:0] $end
   $var wire 32 , rdata_unaligned [31:0] $end
   $var wire  1 < rst_ni $end
   $var wire  1 1 unaligned_is_compressed $end
   $var wire  1 N unused_addr_in $end
   $var wire  1 L valid $end
   $var wire  3 ' valid_d [2:0] $end
   $var wire  3 ( valid_popped [2:0] $end
   $var wire  3 K valid_pushed [2:0] $end
   $var wire  3 I valid_q [2:0] $end
   $var wire  1 M valid_unaligned $end
  $upscope $end
 $upscope $end
$enddefinitions $end


#0
b000000000000000000000000000000000000000000000000000000000000000000000000000000000000000000000000 #
b000 &
b000 '
b000 (
b000 )
0*
b00000000000000000000000000000000 +
b00000000000000000000000000000000 ,
0-
0.
0/
10
11
12
b0000000000000000000000000000001 3
b0000000000000000000000000000001 4
05
b000000000000000000000000000000000000000000000000000000000000000000000000000000000000000000000000 6
b000 9
b0000000000000000000000000000000 :
1;
1<
0=
b00 >
0?
b00000000000000000000000000000000 @
b00000000000000000000000000000000 A
0B
0C
0D
b00000000000000000000000000000000 E
b00000000000000000000000000000000 F
0G
0H
b000 I
b001 J
b000 K
0L
0M
0N
b00000000000000000000000000000010 O
0P
b00000000000000000000000000000011 Q
#1
0;
#2
1;
#3
0;
#4
1;
#5
0;
#6
1;
#7
0;
#8
1;
#9
0;
#10
1;
#11
0;
#12
1;
#13
0;
#14
1;
#15
0;
#16
1;
#17
0;
#18
1;
#19
0;
#20
b011000100101010101011000111011000110001001010101010110001110110001100010010101010101100011101100 #
b001 '
b001 (
b001 )
b01100010010101010101100011101100 +
b01011000111011000110001001010101 ,
b000000000000000000000000000000000000000000000000000000000000000001100010010101010101100011101100 6
1;
0<
1?
b01101011100010110100010101100111 @
b01100010010101010101100011101100 A
1C
b01100010010101010101100011101100 F
b001 K
1L
1N
#21
0;
#22
1;
#23
0;
#24
1;
#25
0;
#26
1;
#27
0;
#28
1;
#29
0;
#30
1;
#31
0;
#32
1;
#33
0;
#34
1;
#35
0;
#36
1;
#37
0;
#38
1;
#39
0;
#40
b010100010101111100000000011111000101000101011111000000000111110001010001010111110000000001111100 #
b01010001010111110000000001111100 +
b00000000011111000101000101011111 ,
01
b000000000000000000000000000000000000000000000000000000000000000001010001010111110000000001111100 6
1;
b00100011100011100001111100101001 @
b01010001010111110000000001111100 A
b01010001010111110000000001111100 F
#41
0;
#42
1;
#43
0;
#44
1;
#45
0;
#46
1;
#47
0;
#48
1;
#49
0;
#50
1;
#51
0;
#52
1;
#53
0;
#54
1;
#55
0;
#56
1;
#57
0;
#58
1;
#59
0;
#60
b000100100010000000001000010101000001001000100000000010000101010000010010001000000000100001010100 #
b111 &
b000 '
b000 (
b000 )
b00010010001000000000100001010100 +
b00001000010101000001001000100000 ,
1-
1.
00
02
b0000000000000000000000000000010 3
b0000000000000000000000000000010 4
1;
0?
b01011011110100000110001011000010 @
b00010010001000000000100001010100 A
1B
0C
b00010010001000000000100001010100 F
1G
b000 K
0L
0N
#61
0;
#62
1;
#63
0;
#64
1;
#65
0;
#66
1;
#67
0;
#68
1;
#69
0;
#70
1;
#71
0;
#72
1;
#73
0;
#74
1;
#75
0;
#76
1;
#77
0;
#78
1;
#79
0;
#80
b000111110001011011101001111010000001111100010110111010011110100000011111000101101110100111101000 #
b000 &
b001 '
b001 (
b001 )
b00011111000101101110100111101000 +
b11101001111010000001111100010110 ,
0-
0.
10
11
12
b0000000000000000000000000000001 3
b0000000000000000000000000000001 4
b000000000000000000000000000000000000000000000000000000000000000000011111000101101110100111101000 6
1;
1?
b01001101101100010010011111111000 @
b00011111000101101110100111101000 A
0B
1C
b00011111000101101110100111101000 F
0G
b001 K
1L
#81
0;
#82
1;
#83
0;
#84
1;
#85
0;
#86
1;
#87
0;
#88
1;
#89
0;
#90
1;
#91
0;
#92
1;
#93
0;
#94
1;
#95
0;
#96
1;
#97
0;
#98
1;
#99
0;
#100
b001001000100001110101000010110000010010001000011101010000101100000100100010000111010100001011000 #
b00100100010000111010100001011000 +
b10101000010110000010010001000011 ,
01
02
b0000000000000000000000000000011 3
b0000000000000000000000000000011 4
b000000000000000000000000000000000000000000000000000000000000000000100100010000111010100001011000 6
b0000000000000000000000000000001 :
1;
b01111100100000111110010001011000 @
b00100100010000111010100001011000 A
0C
1D
b00000000000000000000000000000010 E
b10101000010110000010010001000011 F
#101
0;
#102
1;
#103
0;
#104
1;
#105
0;
#106
1;
#107
0;
#108
1;
#109
0;
#110
1;
#111
0;
#112
1;
#113
0;
#114
1;
#115
0;
#116
1;
#117
0;
#118
1;
#119
0;
#120
b011101011010001010101000110101000111010110100010101010001101010001110101101000101010100011010100 #
b111 &
b000 '
b000 (
b000 )
b01110101101000101010100011010100 +
b10101000110101000111010110100010 ,
1-
1.
00
1;
0?
b00101101000111010101101011101001 @
b01110101101000101010100011010100 A
1B
0D
b10101000110101000111010110100010 F
1G
b000 K
0L
1N
#121
0;
#122
1;
#123
0;
#124
1;
#125
0;
#126
1;
#127
0;
#128
1;
#129
0;
#130
1;
#131
0;
#132
1;
#133
0;
#134
1;
#135
0;
#136
1;
#137
0;
#138
1;
#139
0;
#140
b000000000000000000000000000000000000000000000000000000000000000000000000000000000000000000000000 #
b000 &
b00000000000000000000000000000000 +
b00000000000000000000000000000000 ,
0-
0.
10
11
12
b0000000000000000000000000000001 3
b0000000000000000000000000000000 4
15
b0000000000000000000000000000000 :
1;
1=
b00000000000000000000000000000000 @
b00000000000000000000000000000000 A
0B
b00000000000000000000000000000000 E
b00000000000000000000000000000000 F
0G
0N
#141
0;
#142
1;
#143
0;
#144
1;
#145
0;
#146
1;
#147
0;
#148
1;
#149
0;
#150
1;
#151
0;
#152
1;
#153
0;
#154
1;
#155
0;
#156
1;
#157
0;
#158
1;
#159
0;
#160
b010101001110010010011110101101000101010011100100100111101011010001010100111001001001111010110100 #
b001 '
b001 (
b001 )
b01010100111001001001111010110100 +
b10011110101101000101010011100100 ,
b0000000000000000000000000000001 4
05
b000000000000000000000000000000000000000000000000000000000000000001010100111001001001111010110100 6
1;
0=
1?
b00001000111011011011110110101011 @
b01010100111001001001111010110100 A
1C
b01010100111001001001111010110100 F
b001 K
1L
1N
#161
0;
#162
1;
#163
0;
#164
1;
#165
0;
#166
1;
#167
0;
#168
1;
#169
0;
#170
1;
#171
0;
#172
1;
#173
0;
#174
1;
#175
0;
#176
1;
#177
0;
#178
1;
#179
0;
#180
b001110101001010111111000011101000011101010010101111110000111010000111010100101011111100001110100 #
b111 &
b000 '
b000 (
b000 )
b00111010100101011111100001110100 +
b11111000011101000011101010010101 ,
1-
1.
00
01
02
b0000000000000000000000000000010 3
b0000000000000000000000000000010 4
1;
0?
b01110001111100110010010001010100 @
b00111010100101011111100001110100 A
1B
0C
b00111010100101011111100001110100 F
1G
b000 K
0L
0N
#181
0;
#182
1;
#183
0;
#184
1;
#185
0;
#186
1;
#187
0;
#188
1;
#189
0;
#190
1;
#191
0;
#192
1;
#193
0;
#194
1;
#195
0;
#196
1;
#197
0;
#198
1;
#199
0;
#200
b001000100010001000011010011100000010001000100010000110100111000000100010001000100001101001110000 #
b000 &
1*
b00100010001000100001101001110000 +
b00011010011100000010001000100010 ,
0-
0.
10
11
12
15
b000000000000000000000000000000000000000000000000000000000000000000100010001000100001101001110000 6
b0000000000000000000000000000001 :
1;
1?
b01110011011110111000110111011100 @
b00100010001000100001101001110000 A
0B
1C
1D
b00000000000000000000000000000010 E
b00011010011100000010001000100010 F
0G
b001 K
1L
#201
0;
#202
b001 '
b001 (
b001 )
0*
b0000000000000000000000000000011 3
b0000000000000000000000000000011 4
b0000000000000000000000000000010 :
1;
b00000000000000000000000000000100 E
b00100010001000100001101001110000 F
#203
0;
#204
b000 '
b000 (
b000 )
1*
b0000000000000000000000000000100 3
b0000000000000000000000000000100 4
b0000000000000000000000000000011 :
1;
b00000000000000000000000000000110 E
b00011010011100000010001000100010 F
#205
0;
#206
b001 '
b001 (
b001 )
0*
b0000000000000000000000000000101 3
b0000000000000000000000000000101 4
b0000000000000000000000000000100 :
1;
b00000000000000000000000000001000 E
b00100010001000100001101001110000 F
#207
0;
#208
b000 '
b000 (
b000 )
1*
b0000000000000000000000000000110 3
b0000000000000000000000000000110 4
b0000000000000000000000000000101 :
1;
b00000000000000000000000000001010 E
b00011010011100000010001000100010 F
#209
0;
#210
b001 '
b001 (
b001 )
0*
b0000000000000000000000000000111 3
b0000000000000000000000000000111 4
b0000000000000000000000000000110 :
1;
b00000000000000000000000000001100 E
b00100010001000100001101001110000 F
#211
0;
#212
b000 '
b000 (
b000 )
1*
b0000000000000000000000000001000 3
b0000000000000000000000000001000 4
b0000000000000000000000000000111 :
1;
b00000000000000000000000000001110 E
b00011010011100000010001000100010 F
#213
0;
#214
b001 '
b001 (
b001 )
0*
b0000000000000000000000000001001 3
b0000000000000000000000000001001 4
b0000000000000000000000000001000 :
1;
b00000000000000000000000000010000 E
b00100010001000100001101001110000 F
#215
0;
#216
b000 '
b000 (
b000 )
1*
b0000000000000000000000000001010 3
b0000000000000000000000000001010 4
b0000000000000000000000000001001 :
1;
b00000000000000000000000000010010 E
b00011010011100000010001000100010 F
#217
0;
#218
b001 '
b001 (
b001 )
0*
b0000000000000000000000000001011 3
b0000000000000000000000000001011 4
b0000000000000000000000000001010 :
1;
b00000000000000000000000000010100 E
b00100010001000100001101001110000 F
#219
0;
#220
b010001000000101110101101111111000100010000001011101011011111110001000100000010111010110111111100 #
b01000100000010111010110111111100 +
b10101101111111000100010000001011 ,
01
05
b000000000000000000000000000000000000000000000000000000000000000001000100000010111010110111111100 6
1;
b01000101000101101101110111101001 @
b01000100000010111010110111111100 A
0D
b01000100000010111010110111111100 F
1N
#221
0;
#222
1;
#223
0;
#224
1;
#225
0;
#226
1;
#227
0;
#228
1;
#229
0;
#230
1;
#231
0;
#232
1;
#233
0;
#234
1;
#235
0;
#236
1;
#237
0;
#238
1;
#239
0;
#240
b010111101000100001001010110111000101111010001000010010101101110001011110100010000100101011011100 #
b111 &
b000 '
b000 (
b000 )
b01011110100010000100101011011100 +
b01001010110111000101111010001000 ,
1-
1.
00
02
b0000000000000000000000000001100 3
b0000000000000000000000000001100 4
1;
0?
b00000101000001110010001101100111 @
b01011110100010000100101011011100 A
1B
0C
b01011110100010000100101011011100 F
1G
b000 K
0L
#241
0;
#242
1;
#243
0;
#244
1;
#245
0;
#246
1;
#247
0;
#248
1;
#249
0;
#250
1;
#251
0;
#252
1;
#253
0;
#254
1;
#255
0;
#256
1;
#257
0;
#258
1;
#259
0;
#260
b000101010011111010100100001110000001010100111110101001000011100000010101001111101010010000111000 #
b000 &
b001 '
b001 (
b001 )
b00010101001111101010010000111000 +
b10100100001110000001010100111110 ,
0-
0.
10
11
12
b0000000000000000000000000001011 3
b0000000000000000000000000001011 4
b000000000000000000000000000000000000000000000000000000000000000000010101001111101010010000111000 6
1;
1?
b01010001111010101101001101101011 @
b00010101001111101010010000111000 A
0B
1C
b00010101001111101010010000111000 F
0G
b001 K
1L
#261
0;
#262
1;
#263
0;
#264
1;
#265
0;
#266
1;
#267
0;
#268
1;
#269
0;
#270
1;
#271
0;
#272
1;
#273
0;
#274
1;
#275
0;
#276
1;
#277
0;
#278
1;
#279
0;
#280
b000000000000000000000000000000000000000000000000000000000000000000000000000000000000000000000000 #
b000 '
b000 (
b000 )
b00000000000000000000000000000000 +
b00000000000000000000000000000000 ,
b0000000000000000000000000000001 3
b0000000000000000000000000000000 4
15
b0000000000000000000000000000000 :
1;
1=
0?
b00000000000000000000000000000000 @
b00000000000000000000000000000000 A
0C
b00000000000000000000000000000000 E
b00000000000000000000000000000000 F
b000 K
0L
0N
#281
0;
#282
1;
#283
0;
#284
1;
#285
0;
#286
1;
#287
0;
#288
1;
#289
0;
#290
1;
#291
0;
#292
1;
#293
0;
#294
1;
#295
0;
#296
1;
#297
0;
#298
1;
#299
0;
#300
b011010100010001101000010111011000110101000100011010000101110110001101010001000110100001011101100 #
b111 &
b01101010001000110100001011101100 +
b01000010111011000110101000100011 ,
1-
1.
00
01
02
b0000000000000000000000000000010 3
b0000000000000000000000000000010 4
05
1;
0=
b00111000010101010101100001011100 @
b01101010001000110100001011101100 A
1B
b01101010001000110100001011101100 F
1G
#301
0;
#302
1;
#303
0;
#304
1;
#305
0;
#306
1;
#307
0;
#308
1;
#309
0;
#310
1;
#311
0;
#312
1;
#313
0;
#314
1;
#315
0;
#316
1;
#317
0;
#318
1;
#319
0;
#320
b011110100110110110001101001111000111101001101101100011010011110001111010011011011000110100111100 #
b000 &
b001 '
b001 (
b001 )
b01111010011011011000110100111100 +
b10001101001111000111101001101101 ,
0-
0.
10
11
12
b0000000000000000000000000000001 3
b0000000000000000000000000000001 4
b000000000000000000000000000000000000000000000000000000000000000001111010011011011000110100111100 6
1;
1?
b00101010010010000111110010110000 @
b01111010011011011000110100111100 A
0B
1C
b01111010011011011000110100111100 F
0G
b001 K
1L
#321
0;
#322
1;
#323
0;
#324
1;
#325
0;
#326
1;
#327
0;
#328
1;
#329
0;
#330
1;
#331
0;
#332
1;
#333
0;
#334
1;
#335
0;
#336
1;
#337
0;
#338
1;
#339
0;
#340
b010101000010001010001001111011000101010000100010100010011110110001010100001000101000100111101100 #
b01010100001000101000100111101100 +
b10001001111011000101010000100010 ,
b000000000000000000000000000000000000000000000000000000000000000001010100001000101000100111101100 6
1;
b01001011010110001000111101010100 @
b01010100001000101000100111101100 A
b01010100001000101000100111101100 F
#341
0;
#342
1;
#343
0;
#344
1;
#345
0;
#346
1;
#347
0;
#348
1;
#349
0;
#350
1;
#351
0;
#352
1;
#353
0;
#354
1;
#355
0;
#356
1;
#357
0;
#358
1;
#359
0;
#360
b011101100100010010100100010111000111011001000100101001000101110001110110010001001010010001011100 #
b111 &
b000 '
b000 (
b000 )
b01110110010001001010010001011100 +
b10100100010111000111011001000100 ,
1-
1.
00
01
02
b0000000000000000000000000000010 3
b0000000000000000000000000000010 4
1;
0?
b01101101111010010001101100011000 @
b01110110010001001010010001011100 A
1B
0C
b01110110010001001010010001011100 F
1G
b000 K
0L
#361
0;
#362
1;
#363
0;
#364
1;
#365
0;
#366
1;
#367
0;
#368
1;
#369
0;
#370
1;
#371
0;
#372
1;
#373
0;
#374
1;
#375
0;
#376
1;
#377
0;
#378
1;
#379
0;
#380
b001000111111100111000001001111000010001111111001110000010011110000100011111110011100000100111100 #
b000 &
b001 '
b001 (
b001 )
b00100011111110011100000100111100 +
b11000001001111000010001111111001 ,
0-
0.
10
11
12
b0000000000000000000000000000001 3
b0000000000000000000000000000001 4
b000000000000000000000000000000000000000000000000000000000000000000100011111110011100000100111100 6
1;
1?
b00110010111111111111100100000010 @
b00100011111110011100000100111100 A
0B
1C
b00100011111110011100000100111100 F
0G
b001 K
1L
#381
0;
#382
1;
#383
0;
#384
1;
#385
0;
#386
1;
#387
0;
#388
1;
#389
0;
#390
1;
#391
0;
#392
1;
#393
0;
#394
1;
#395
0;
#396
1;
#397
0;
#398
1;
#399
0;
#400
b001001110101101011000111100101000010011101011010110001111001010000100111010110101100011110010100 #
b000 '
b000 (
b000 )
1*
b00100111010110101100011110010100 +
b11000111100101000010011101011010 ,
b0000000000000000000000000000010 3
b0000000000000000000000000000010 4
15
b000000000000000000000000000000000000000000000000000000000000000000100111010110101100011110010100 6
b0000000000000000000000000000001 :
1;
b01100100100110111011011101111100 @
b00100111010110101100011110010100 A
1D
b00000000000000000000000000000010 E
b11000111100101000010011101011010 F
#401
0;
#402
b001 '
b001 (
b001 )
0*
b0000000000000000000000000000011 3
b0000000000000000000000000000011 4
b0000000000000000000000000000010 :
1;
b00000000000000000000000000000100 E
b00100111010110101100011110010100 F
#403
0;
#404
b000 '
b000 (
b000 )
1*
b0000000000000000000000000000100 3
b0000000000000000000000000000100 4
b0000000000000000000000000000011 :
1;
b00000000000000000000000000000110 E
b11000111100101000010011101011010 F
#405
0;
#406
b001 '
b001 (
b001 )
0*
b0000000000000000000000000000101 3
b0000000000000000000000000000101 4
b0000000000000000000000000000100 :
1;
b00000000000000000000000000001000 E
b00100111010110101100011110010100 F
#407
0;
#408
b000 '
b000 (
b000 )
1*
b0000000000000000000000000000110 3
b0000000000000000000000000000110 4
b0000000000000000000000000000101 :
1;
b00000000000000000000000000001010 E
b11000111100101000010011101011010 F
#409
0;
#410
b001 '
b001 (
b001 )
0*
b0000000000000000000000000000111 3
b0000000000000000000000000000111 4
b0000000000000000000000000000110 :
1;
b00000000000000000000000000001100 E
b00100111010110101100011110010100 F
#411
0;
#412
b000 '
b000 (
b000 )
1*
b0000000000000000000000000001000 3
b0000000000000000000000000001000 4
b0000000000000000000000000000111 :
1;
b00000000000000000000000000001110 E
b11000111100101000010011101011010 F
#413
0;
#414
b001 '
b001 (
b001 )
0*
b0000000000000000000000000001001 3
b0000000000000000000000000001001 4
b0000000000000000000000000001000 :
1;
b00000000000000000000000000010000 E
b00100111010110101100011110010100 F
#415
0;
#416
b000 '
b000 (
b000 )
1*
b0000000000000000000000000001010 3
b0000000000000000000000000001010 4
b0000000000000000000000000001001 :
1;
b00000000000000000000000000010010 E
b11000111100101000010011101011010 F
#417
0;
#418
b001 '
b001 (
b001 )
0*
b0000000000000000000000000001011 3
b0000000000000000000000000001011 4
b0000000000000000000000000001010 :
1;
b00000000000000000000000000010100 E
b00100111010110101100011110010100 F
#419
0;
#420
b000111001111000100001111110110000001110011110001000011111101100000011100111100010000111111011000 #
b111 &
b000 '
b000 (
b000 )
b00011100111100010000111111011000 +
b00001111110110000001110011110001 ,
1-
1.
00
01
02
b0000000000000000000000000001100 3
b0000000000000000000000000001100 4
05
1;
0?
b00111001001110000110010101110101 @
b00011100111100010000111111011000 A
1B
0C
0D
b00011100111100010000111111011000 F
1G
b000 K
0L
1N
#421
0;
#422
1;
#423
0;
#424
1;
#425
0;
#426
1;
#427
0;
#428
1;
#429
0;
#430
1;
#431
0;
#432
1;
#433
0;
#434
1;
#435
0;
#436
1;
#437
0;
#438
1;
#439
0;
#440
b000101011011010110101111010111000001010110110101101011110101110000010101101101011010111101011100 #
b000 &
b001 '
b001 (
b001 )
b00010101101101011010111101011100 +
b10101111010111000001010110110101 ,
0-
0.
10
11
12
b0000000000000000000000000001011 3
b0000000000000000000000000001011 4
b000000000000000000000000000000000000000000000000000000000000000000010101101101011010111101011100 6
1;
1?
b00011000000000010001010110111110 @
b00010101101101011010111101011100 A
0B
1C
b00010101101101011010111101011100 F
0G
b001 K
1L
0N
#441
0;
#442
1;
#443
0;
#444
1;
#445
0;
#446
1;
